{
  "prix_augmentes": [
    {
      "list_id": 3821,
      "prix_base": 9500,
      "name": "Farine De Bl\u00e9 Multi Usage 1 Kg",
      "prix_comparaison": 8100,
      "variation": -1400
    }
  ],
  "prix_diminues": [
    {
      "list_id": 3821,
      "prix_base": 9500,
      "name": "Farine De Bl\u00e9 Multi Usage 1 Kg",
      "prix_comparaison": 8100,
      "variation": -1400
    }
  ],
  "indices_prix_plus_eleves": [
    {
      "list_id": 3821,
      "name": "Farine De Bl\u00e9 Multi Usage 1 Kg",
      "prix_base": 9500,
      "prix_comparaison": 8100,
      "indice_prix": 85.26315789473684
    }
  ],
  "indices_prix_plus_faibles": [
    {
      "list_id": 3821,
      "name": "Farine De Bl\u00e9 Multi Usage 1 Kg",
      "prix_base": 9500,
      "prix_comparaison": 8100,
      "indice_prix": 85.26315789473684
    }
  ]
}