{
  "prix_augmentes": [
    {
      "cle": "protectionshygienefeminine_15093servietteshygieniquesultramaxix24_html",
      "name": "Serviettes hygi\u00e9niques ultra maxi x24",
      "prix_base": 7900,
      "prix_comparaison": 9000,
      "variation": 1100
    }
  ],
  "prix_diminues": [
    {
      "cle": "nappesserviettesessuietout_14065serviettesdetable60pieces_html",
      "name": "Mini-serviettes de table 60 pi\u00e8ces",
      "prix_base": 1100,
      "prix_comparaison": 1190,
      "variation": 90
    }
  ],
  "indices_prix_plus_eleves": [
    {
      "cle": "pates_9004coquillettes500g_html",
      "name": "Coquillettes 500g",
      "prix_base": 5500,
      "prix_comparaison": 6500,
      "indice_prix": 118.18181818181819
    }
  ],
  "indices_prix_plus_faibles": [
    {
      "cle": "eauxgazeusesaromatisees_4663boissongazeusecristal150cl_html",
      "name": "Boisson gazeuse cristal 150cl",
      "prix_base": 4290,
      "prix_comparaison": 4600,
      "indice_prix": 107.22610722610723
    }
  ]
}