{
  "Variation de prix": [
    {
      "list_id": 368,
      "name": "Sucre Blanc 1 Kg",
      "prix_base": 11300,
      "prix_comparaison": 11300,
      "variation": 0,
      "indice_prix": 100.0
    },
    {
      "list_id": 370,
      "name": "Sucre Blanc 250 g",
      "prix_base": 2900,
      "prix_comparaison": 2900,
      "variation": 0,
      "indice_prix": 100.0
    },
    {
      "list_id": 9687,
      "name": "Sucre blanc 1 kg",
      "prix_base": 7950,
      "prix_comparaison": 7950,
      "variation": 0,
      "indice_prix": 100.0
    }
  ]
}