{
  "Variation de prix": [
    {
      "cle": "promo2023_7291rizblancdelitasy50kg_html",
      "name": "Riz blanc de l'Itasy 50kg",
      "prix_base": 184000,
      "prix_comparaison": 184000,
      "variation": 0,
      "indice_prix": 100.0
    },
    {
      "cle": "riz_7289rizblancdeitasy5kg_html",
      "name": "Riz blanc de l'Itasy 5kg",
      "prix_base": 18400,
      "prix_comparaison": 18400,
      "variation": 0,
      "indice_prix": 100.0
    },
    {
      "cle": "promo2023_1894huiledesoja20lhina_html",
      "name": "Huile de soja Hina 20L",
      "prix_base": 179400,
      "prix_comparaison": 179400,
      "variation": 0,
      "indice_prix": 100.0
    }
  ]
}