{
  "Variation de prix": [
    {
      "cle": "ordinateurportable_133927apple14macbookprom32023ram8gostockage1toargentazerty0195949015205_html",
      "name": "Apple - 14 - MacBook Pro M3 (2023) - RAM 8Go - Stockage 1To - Argent - Azerty",
      "prix_base": 10757000,
      "prix_comparaison": 10757000,
      "variation": 0,
      "indice_prix": 100.0
    },
    {
      "cle": "spacompletkitspajacuzzi_88160spagonflablebestwaylayzspamaldives201x201x80cm5a7placescarrecouverturepompecartouchediffuseur6942138975970_html",
      "name": "Spa gonflable BESTWAY - Lay-Z-Spa Maldives - 201 x 201 x 80 cm - 5 a 7 places - Carr\u00e9 (Couverture, pompe, cartouche, diffuseur,",
      "prix_base": 10205000,
      "prix_comparaison": 10205000,
      "variation": 0,
      "indice_prix": 100.0
    },
    {
      "cle": "ordinateurportable_137455pcportablegamingerazernberazerbeastx40173qhd240hzi914900hx32gossd1tortx4080azerty4061275228410_html",
      "name": "PC portable Gaming - ERAZER - NB ERAZER BEAST X40 - 17,3\u201d QHD 240Hz - i9-14900HX - 32Go - SSD 1To - RTX 4080 - AZERTY",
      "prix_base": 15762000,
      "prix_comparaison": 15762000,
      "variation": 0,
      "indice_prix": 100.0
    }
  ]
}