{
  "Variation de prix": [
    {
      "cle": "produit_huilesoja1l_",
      "name": "Huile de Soja Hina\u2122 1L | Riche en Om\u00e9ga 3 et en Vitamine E",
      "prix_base": 225,
      "prix_comparaison": 225,
      "variation": 0,
      "indice_prix": 100.0
    },
    {
      "cle": "produit_rizblancmakaliokasupermarchemg25kgoriginemadagascar_",
      "name": "Riz blanc Makalioka Supermarch\u00e9.mg\u2122 25kg | Origine Madagascar",
      "prix_base": 2464,
      "prix_comparaison": 2464,
      "variation": 0,
      "indice_prix": 100.0
    },
    {
      "cle": "produit_rizmakalioka5kg_",
      "name": "Riz blanc Makalioka Supermarch\u00e9.mg\u2122 5kg | Origine Madagascar",
      "prix_base": 504,
      "prix_comparaison": 504,
      "variation": 0,
      "indice_prix": 100.0
    }
  ]
}